{"cameraMode":{"drawMode":0,"name":"Shaded","section":"Shading Mode"},"sceneLighting":true,"audioPlay":false,"sceneViewState":{"m_AlwaysRefresh":false,"showFog":true,"showSkybox":true,"showFlares":true,"showImageEffects":true,"showParticleSystems":true,"showVisualEffectGraphs":true,"m_FxEnabled":true},"in2DMode":false,"pivot":{"x":95.55355072021485,"y":-23.14461326599121,"z":145.09027099609376},"rotation":{"x":0.1345711201429367,"y":0.25694504380226138,"z":-0.036171212792396548,"w":0.9562740921974182},"size":85.30250549316406,"orthographic":false}